sphinx_changelog/__init__.py
sphinx_changelog/directive.py
sphinx_changelog/towncrier.py
sphinx_changelog/version.py
sphinx_changelog-1.6.0.dist-info/LICENSE.rst
sphinx_changelog-1.6.0.dist-info/METADATA
sphinx_changelog-1.6.0.dist-info/WHEEL
sphinx_changelog-1.6.0.dist-info/top_level.txt
sphinx_changelog-1.6.0.dist-info/RECORD
