Metadata-Version: 2.1
Name: sphinx_changelog
Version: 1.6.0
Summary: A changelog renderer for sphinx.
Home-page: https://openastronomy.org
Author: SunPy and OpenAstronomy Developers
Author-email: stuart@cadair.com
License: BSD 3-Clause
Requires-Python: >=3.8
License-File: licenses/LICENSE.rst
Requires-Dist: sphinx
Requires-Dist: towncrier==24.8.0
Provides-Extra: docs
Requires-Dist: sphinx; extra == "docs"
Requires-Dist: sphinx-automodapi; extra == "docs"
Provides-Extra: test
Requires-Dist: pytest; extra == "test"
Requires-Dist: pytest-cov; extra == "test"
